CHANGES.rst
LICENSE
MANIFEST.in
README.rst
TODO.rst
bootstrap.sh
setup.cfg
setup.py
tox.ini
clusterprocessing/__init__.py
clusterprocessing/version.py
clusterprocessing.egg-info/PKG-INFO
clusterprocessing.egg-info/SOURCES.txt
clusterprocessing.egg-info/dependency_links.txt
clusterprocessing.egg-info/top_level.txt
clusterprocessing.egg-info/zip-safe
docs/Makefile
docs/check_docs.py
docs/make.bat
docs/requirements.txt
docs/build/doctrees/changes.doctree
docs/build/doctrees/environment.pickle
docs/build/doctrees/index.doctree
docs/build/doctrees/roadmap.doctree
docs/build/html/.buildinfo
docs/build/html/changes.html
docs/build/html/genindex.html
docs/build/html/index.html
docs/build/html/objects.inv
docs/build/html/roadmap.html
docs/build/html/search.html
docs/build/html/searchindex.js
docs/build/html/_sources/changes.txt
docs/build/html/_sources/index.txt
docs/build/html/_sources/roadmap.txt
docs/build/html/_static/ajax-loader.gif
docs/build/html/_static/basic.css
docs/build/html/_static/comment-bright.png
docs/build/html/_static/comment-close.png
docs/build/html/_static/comment.png
docs/build/html/_static/default.css
docs/build/html/_static/doctools.js
docs/build/html/_static/down-pressed.png
docs/build/html/_static/down.png
docs/build/html/_static/file.png
docs/build/html/_static/jquery.js
docs/build/html/_static/minus.png
docs/build/html/_static/plus.png
docs/build/html/_static/pygments.css
docs/build/html/_static/rtd.css
docs/build/html/_static/searchtools.js
docs/build/html/_static/sidebar.js
docs/build/html/_static/underscore.js
docs/build/html/_static/up-pressed.png
docs/build/html/_static/up.png
docs/build/html/_static/websupport.js
docs/source/changes.rst
docs/source/conf.py
docs/source/index.rst
docs/source/roadmap.rst
docs/source/_static/rtd.css
docs/source/_templates/layout.html
docs/source/examples/localcluster.py
examples/localcluster.py
fabfile/__init__.py
fabfile/utils.py
tests/__init__.py
tests/__init__.pyc
tests/conftest.py
tests/conftest.pyc
tests/main.py
tests/main.pyc
tests/test_cluster.py
tests/__pycache__/test_cluster.cpython-27-PYTEST.pyc