Metadata-Version: 1.1
Name: clusterprocessing
Version: 0.0.0.dev
Summary: TBA
Home-page: TBA
Author: James Mills
Author-email: James Mills, prologic at shortcircuit dot net dot au
License: TBA
Download-URL: TBA
Platform: POSIX
